ndfes/AutoEquil.py
ndfes/Bspline.py
ndfes/EvalT.py
ndfes/FES.py
ndfes/FTSM.py
ndfes/GPR.py
ndfes/GridUtils.py
ndfes/MBAR.py
ndfes/Metafile.py
ndfes/PCV.py
ndfes/PathData.py
ndfes/PathUtils.py
ndfes/PlotUtils.py
ndfes/RBF.py
ndfes/ReadCheckpoint.py
ndfes/ScriptUtils.py
ndfes/SmoothCurve.py
ndfes/SpatialBin.py
ndfes/SpatialDim.py
ndfes/Trajectory.py
ndfes/VirtualGrid.py
ndfes/WAVG.py
ndfes/__init__.py
ndfes/scripts.py
ndfes/vFEP.py
ndfes/amber/Disang.py
ndfes/amber/Geometry.py
ndfes/amber/Reader.py
ndfes/amber/Restraint.py
ndfes/amber/__init__.py
ndfes/bin/ndfes
ndfes/bin/ndfes-AvgFESs.py
ndfes/bin/ndfes-CheckEquil.py
ndfes/bin/ndfes-CombineMetafiles.py
ndfes/bin/ndfes-PrepareAmberData.py
ndfes/bin/ndfes-PrintFES.py
ndfes/bin/ndfes-genbias
ndfes/bin/ndfes-genbias_omp
ndfes/bin/ndfes-path
ndfes/bin/ndfes-path-analyzesims.py
ndfes/bin/ndfes-path-prepguess.py
ndfes/bin/ndfes-path_omp
ndfes/bin/ndfes_omp
ndfes/constants/Conversions.py
ndfes/constants/PeriodicTable.py
ndfes/constants/__init__.py
ndfes/deprecated/DensityEst.py
ndfes/deprecated/DensityString.py
ndfes/deprecated/OptUtils.py
ndfes/deprecated/__init__.py
ndfes/gaussian/GaussianOutput.py
ndfes/gaussian/__init__.py
ndfes/include/nlopt.h
ndfes/include/nlopt.hpp
ndfes/include/openblas/cblas.h
ndfes/include/openblas/f77blas.h
ndfes/include/openblas/lapack.h
ndfes/include/openblas/lapacke.h
ndfes/include/openblas/lapacke_config.h
ndfes/include/openblas/lapacke_example_aux.h
ndfes/include/openblas/lapacke_mangling.h
ndfes/include/openblas/lapacke_utils.h
ndfes/include/openblas/openblas_config.h
ndfes/lib64/libnlopt.so
ndfes/lib64/libnlopt.so.0
ndfes/lib64/libnlopt.so.0.12.0
ndfes/lib64/libopenblas.so
ndfes/lib64/libopenblas.so.0
ndfes/lib64/libopenblas.so.0.3
ndfes/lib64/cmake/OpenBLAS/OpenBLASConfig.cmake
ndfes/lib64/cmake/OpenBLAS/OpenBLASConfigVersion.cmake
ndfes/lib64/cmake/OpenBLAS/OpenBLASTargets-release.cmake
ndfes-3.5.8.dist-info/METADATA
ndfes-3.5.8.dist-info/WHEEL
ndfes-3.5.8.dist-info/entry_points.txt
ndfes-3.5.8.dist-info/RECORD
