Metadata-Version: 2.2
Name: ndfes
Version: 3.5.8
Summary: Companion library to the ndfes C++ program for analyzing umbrella sampling
Keywords: ndfes
Author-Email: "Timothy J. Giese" <TimothyJGiese@gmail.com>
Classifier: Programming Language :: Python :: 3
Classifier: Development Status :: 5 - Production/Stable
Requires-Python: >=3.7
Requires-Dist: numpy
Requires-Dist: matplotlib
Requires-Dist: scipy
Requires-Dist: pyyaml
Requires-Dist: netCDF4
Requires-Dist: setuptools
Requires-Dist: importlib
Requires-Dist: importlib-metadata
